airflow_kpvco/__init__.py
airflow_kpvco/kubernetes_pvc_manager.py
airflow_kpvco/kubernetes_pvc_operator.py
airflow_kpvco/kubernetes_util.py
airflow_kube_pvc_operator-0.0.1.dist-info/METADATA
airflow_kube_pvc_operator-0.0.1.dist-info/WHEEL
airflow_kube_pvc_operator-0.0.1.dist-info/top_level.txt
airflow_kube_pvc_operator-0.0.1.dist-info/RECORD
