Metadata-Version: 2.1
Name: airflow-kube-pvc-operator
Version: 0.0.1
Summary: Kubernetes pvc operator for Airflow
Home-page: UNKNOWN
Author: EliMor
Author-email: elimor.github@gmail.com
License: Apache License 2.0
Platform: UNKNOWN
Classifier: Programming Language :: Python :: 3.6
Classifier: Programming Language :: Python :: 3.7
Classifier: Programming Language :: Python :: 3.8
Classifier: Programming Language :: Python :: 3.9
Classifier: License :: OSI Approved :: Apache Software License
Requires-Dist: airflow-kube-base-operator (>=0.0.1)
Provides-Extra: tests
Requires-Dist: pytest ; extra == 'tests'
